ainject/__init__.py
ainject/ainject.py
ainject-0.0.3.dist-info/METADATA
ainject-0.0.3.dist-info/WHEEL
ainject-0.0.3.dist-info/top_level.txt
ainject-0.0.3.dist-info/RECORD
