Metadata-Version: 2.1
Name: ainject
Version: 0.0.3
Summary: Simple asynchronous dependency injector for python
Home-page: https://github.com/pohmelie/ainject
Author: pohmelie
Author-email: multisosnooley@gmail.com
License: WTFPL
Platform: UNKNOWN
Classifier: Programming Language :: Python
Classifier: Programming Language :: Python :: 3
